emaileasily/__init__.py
emaileasily/emaileasily.py
emaileasily-0.2.0.dist-info/LICENSE
emaileasily-0.2.0.dist-info/METADATA
emaileasily-0.2.0.dist-info/WHEEL
emaileasily-0.2.0.dist-info/top_level.txt
emaileasily-0.2.0.dist-info/RECORD
