Metadata-Version: 2.1
Name: emaileasily
Version: 0.2.0
Summary: A python email library to send and read emails.
Home-page: https://github.com/erastusnzula/easy-email
Author: Erastus Nzula
Author-email: nzulaerastus@gmail.com
License: MIT
Platform: UNKNOWN
Classifier: License :: OSI Approved :: MIT License
Classifier: Programming Language :: Python :: 3 :: Only
Classifier: Programming Language :: Python :: 3.10
Classifier: Programming Language :: Python :: 3.9
Classifier: Programming Language :: Python :: 3.8
Classifier: Programming Language :: Python :: 3.7
Classifier: Programming Language :: Python :: 3.6
Classifier: Operating System :: OS Independent
Requires-Python: >=3.6
License-File: LICENSE
